simple_httpfs/__init__.py
simple_httpfs/__main__.py
simple_httpfs/httpfs.py
simple_httpfs-0.4.12.dist-info/LICENSE
simple_httpfs-0.4.12.dist-info/METADATA
simple_httpfs-0.4.12.dist-info/WHEEL
simple_httpfs-0.4.12.dist-info/entry_points.txt
simple_httpfs-0.4.12.dist-info/top_level.txt
simple_httpfs-0.4.12.dist-info/RECORD
