Metadata-Version: 2.1
Name: simple-httpfs
Version: 0.4.12
Summary: A simple FUSE filesystem for reading http files
Home-page: https://github.com/higlass/simple-httpfs
Author: Peter Kerpedjiev
Author-email: pkerpedjiev@gmail.com
License: MIT
Platform: UNKNOWN
Requires-Dist: boto3
Requires-Dist: diskcache
Requires-Dist: fusepy
Requires-Dist: requests
Requires-Dist: slugid
Requires-Dist: tenacity
